Metadata-Version: 1.1
Name: django-event-logging
Version: 0.1.1
Summary: Insert event into database for logging purpose
Home-page: https://github.com/ducminhgd/django-event-logging
Author: Gia Duong Duc Minh
Author-email: giaduongducminh@gmail.com
License: UNKNOWN
Platform: UNKNOWN
Classifier: Environment :: Web Environment
Classifier: Framework :: Django
Classifier: Framework :: Django :: 1.11
Classifier: Intended Audience :: Developers
Classifier: Operating System :: OS Independent
Classifier: Programming Language :: Python
Classifier: Programming Language :: Python :: 3.6
Classifier: Topic :: Internet :: WWW/HTTP
Classifier: Topic :: Internet :: WWW/HTTP :: Dynamic Content
